solidserver/__init__.py
solidserver/driver.py
externaldns_solidserver-0.1.6.dist-info/LICENSE
externaldns_solidserver-0.1.6.dist-info/METADATA
externaldns_solidserver-0.1.6.dist-info/WHEEL
externaldns_solidserver-0.1.6.dist-info/entry_points.txt
externaldns_solidserver-0.1.6.dist-info/top_level.txt
externaldns_solidserver-0.1.6.dist-info/RECORD
