Metadata-Version: 2.1
Name: externaldns-solidserver
Version: 0.1.6
Summary: External DNS implemtation for EfficientIP SolidServer
Home-page: https://gricad-gitlab.univ-grenoble-alpes.fr/gricad/openstack/    externaldns-solidserver/blob/master/driver.py
Author: Rémi Cailletaud
Author-email: remche@remche.org
License: UNKNOWN
Platform: Any
Classifier: Development Status :: 3 - Alpha
Classifier: License :: OSI Approved :: Apache Software License
Classifier: Programming Language :: Python
Classifier: Programming Language :: Python :: 2
Classifier: Programming Language :: Python :: 2.7
Classifier: Programming Language :: Python :: 3
Classifier: Programming Language :: Python :: 3.5
Classifier: Intended Audience :: Developers
Classifier: Environment :: Console
Provides: neutron.services.externaldns.drivers.solidserver
